secretnote/__init__.py
secretnote/__main__.py
secretnote/scql/__init__.py
secretnote/scql/.jupyter/config_dev.py
secretnote/scql/server/__init__.py
secretnote/scql/server/__main__.py
secretnote/scql/server/app.py
secretnote/scql/server/py.typed
secretnote/scql/server/utils.py
secretnote/scql/server/services/__init__.py
secretnote/scql/server/services/_proxy_handler.py
secretnote/scql/server/services/agent_handlers.py
secretnote/scql/server/services/broker_handlers.py
secretnote/scql/server/services/broker_manager.py
secretnote/scql/server/services/contents_handlers.py
secretnote/scql/server/services/pages_handlers.py
secretnote/scql/www/1215.async.js
secretnote/scql/www/1256.async.js
secretnote/scql/www/1534.async.js
secretnote/scql/www/1644.async.js
secretnote/scql/www/1673.async.js
secretnote/scql/www/2016.async.js
secretnote/scql/www/2031.async.js
secretnote/scql/www/2220.chunk.css
secretnote/scql/www/2300.async.js
secretnote/scql/www/2310.async.js
secretnote/scql/www/2514.async.js
secretnote/scql/www/2594.async.js
secretnote/scql/www/2825.async.js
secretnote/scql/www/2845.async.js
secretnote/scql/www/2913.async.js
secretnote/scql/www/3006.async.js
secretnote/scql/www/3040.async.js
secretnote/scql/www/3094.async.js
secretnote/scql/www/3199.async.js
secretnote/scql/www/3315.async.js
secretnote/scql/www/3526.async.js
secretnote/scql/www/3559.async.js
secretnote/scql/www/3608.async.js
secretnote/scql/www/3647.async.js
secretnote/scql/www/3726.async.js
secretnote/scql/www/3838.async.js
secretnote/scql/www/3878.async.js
secretnote/scql/www/4059.async.js
secretnote/scql/www/4231.async.js
secretnote/scql/www/4264.async.js
secretnote/scql/www/4463.async.js
secretnote/scql/www/4879.async.js
secretnote/scql/www/4971.async.js
secretnote/scql/www/5053.async.js
secretnote/scql/www/528.async.js
secretnote/scql/www/5559.async.js
secretnote/scql/www/5575.async.js
secretnote/scql/www/5580.async.js
secretnote/scql/www/5709.async.js
secretnote/scql/www/5759.async.js
secretnote-0.0.52.dist-info/METADATA
secretnote-0.0.52.dist-info/WHEEL
secretnote-0.0.52.dist-info/entry_points.txt
secretnote-0.0.52.dist-info/RECORD
