Metadata-Version: 2.4
Name: secretnote
Version: 0.0.52
Summary: Server for SecretNote (Python) App
Author-email: "wenyu.jqq" <wenyu.jqq@antgroup.com>, Tony Wu <tonywu6@protonmail.com>, "zhuoxu.zx" <zhuoxu.zx@antgroup.com>
License: Apache-2.0
Classifier: Development Status :: 3 - Alpha
Classifier: License :: OSI Approved :: Apache Software License
Requires-Python: <3.12,>=3.10
Requires-Dist: dataset>=1.6.2
Requires-Dist: ipykernel>=6.24.0
Requires-Dist: ipywidgets>=8.1.1
Requires-Dist: jupyter-lsp>=2.2.0
Requires-Dist: jupyter-resource-usage~=1.0
Requires-Dist: jupyter-server-proxy
Requires-Dist: jupyter-server~=2.7
Requires-Dist: python-lsp-server==1.8.2
